espy_pdfier/__init__.py
espy_pdfier/service/__init__.py
espy_pdfier/service/crm.py
espy_pdfier/service/img_serv.py
espy_pdfier/service/schema.py
espy_pdfier/service/service.py
espy_pdfier/util/CONSTANTS.py
espy_pdfier/util/__init__.py
espy_pdfier-0.27.dist-info/LICENSE
espy_pdfier-0.27.dist-info/METADATA
espy_pdfier-0.27.dist-info/WHEEL
espy_pdfier-0.27.dist-info/top_level.txt
espy_pdfier-0.27.dist-info/RECORD
